seven_seg/seven_seg_src.v
module frequency_divider (
    input clk,          // Input clock (100 MHz)
    output reg slow_clk // Output slow clock (1 Hz)
);
    reg [26:0] counter;  // 27-bit counter for division

    always @(posedge clk) begin
        if (counter == 27'd50_000_000) begin  // 50 million clock cycles (100 MHz / 2)
            slow_clk <= ~slow_clk; // Toggle slow clock every 50 million cycles
            counter <= 27'd0;
        end else begin
            counter <= counter + 1;
        end
    end
endmodule

module seven_segment_decoder (
    input [3:0] num,           // 4-bit binary input (0-9)
    output reg [6:0] seg       // 7-segment output (7 segments)
);
    always @(*) begin
        case (num)
            4'd0: seg = 7'b1111110; // 0
            4'd1: seg = 7'b0110000; // 1
            4'd2: seg = 7'b1101101; // 2
            4'd3: seg = 7'b1111001; // 3
            4'd4: seg = 7'b0110011; // 4
            4'd5: seg = 7'b1011011; // 5
            4'd6: seg = 7'b1011111; // 6
            4'd7: seg = 7'b1110000; // 7
            4'd8: seg = 7'b1111111; // 8
            4'd9: seg = 7'b1111011; // 9
            default: seg = 7'b0000000; // Default (off state)
        endcase
    end
endmodule

module sequence_generator (
    input clk,                // Input clock (100 MHz)
    output [6:0] seg         // 7-segment display output
);
    wire slow_clk;           // Slow clock (1 Hz)
    reg [3:0] num = 4'd0;    // 4-bit counter (0-9)
    
    // Instantiate the frequency divider (to slow down the clock)
    frequency_divider freq_div (
        .clk(clk),
        .slow_clk(slow_clk)
    );

    // Instantiate the 7-segment decoder
    seven_segment_decoder seg_decoder (
        .num(num),
        .seg(seg)
    );

    // Counter logic: Increment the number on each slow clock tick
    always @(posedge slow_clk) begin
        if (num == 4'd9) begin
            num <= 4'd0;  // Reset to 0 after 9
        end else begin
            num <= num + 1;  // Increment the counter
        end
    end
endmodule

seven_seg/tb_seven_seg.v
module tb_sequence_generator;

    // Inputs
    reg clk;                // Input clock (100 MHz)
    
    // Outputs
    wire [6:0] seg;        // 7-segment display output (7 segments)

    // Instantiate the sequence generator (Device Under Test)
    sequence_generator uut (
        .clk(clk),
        .seg(seg)
    );

    // Clock generation: 10 ns period clock (100 MHz)
    always begin
        #5 clk = ~clk; // Toggle clock every 5ns for a 100 MHz clock
    end

    initial begin
        // Initialize signals
        clk = 0;

        // Wait for some time to simulate the behavior (let the counter run)
        #1000000;  // Wait for approximately 10 seconds (for a 1 Hz output)

        // Finish simulation
        $finish;
    end

    // Display output on simulation console
    initial begin
        $monitor("Time = %t, seg = %b", $time, seg);
    end

endmodule

seven_seg/project_1.sim/sim_1/behav/xsim/dump.vcd
$date
   Sun Apr  6 11:19:57 2025
$end

$version
  2023.2
$end

$timescale
  1ps
$end

$scope module tb_sequence_generator $end
$scope module uut $end
$var wire 4 ! num [3:0] $end
$upscope $end
$upscope $end
$enddefinitions $end

#0
$dumpvars
b0 !
$end

#35000
b1 !

#115000
b10 !

#195000
b11 !

#275000
b100 !

#355000
b101 !

#435000
b110 !

#515000
b111 !

#595000
b1000 !

#675000
b1001 !

#755000
b0 !

#835000
b1 !

#915000
b10 !

#995000
b11 !
